{
  "name": "Lenora Frazier",
  "age": 39,
  "address": {
    "street": "Gubu Key",
    "city": "Safmalhu",
    "state": "IN",
    "zip": "39460"
  },
  "contact": {
    "phone": "(748) 436-3870",
    "servicePhone": "800844572"
  },
  "birthday": "1997-09-06T08:16:17.901Z",
  "ip": "112.132.238.232",
  "foo": "bar",
  "profile": {
    "about": "Vit kej gosaflaw ehi botonrak luvdag punhij sepu tisas na hiw fu. Velsas tigolgif hobahanih vaci teho emubi saadodi ijici idu usoriga alibima ako ok ibdon. Pimasevep wijco aga pibouvo sa gum nonudif teowsuc bozutu wamuf rowuven tuhi givose honsevoru.",
    "bio": "No evcana bigebu asi fukmucfig cifruvja socwaj eve iddieb befutav kauv kalabhu raune mawacog netifu. Bociw lofu apic ijekicjew ginikoga tohru huczuzbi huwkapilo la morebic nepfobniw he. Dev ca betov javnacjav coblit fos kawged pobahud sejraap ozeto muh leahme ki sugade."
  },
  "apiKey": "d0d8b25da864ad830e48881f8f301aa8abfa7110459652c51c01d5c16ae209c5",
  "currency": {
    "code": "LSL",
    "name": "Lesotho Loti"
  }
}