{
  "name": "Kenneth Day",
  "age": 40,
  "address": {
    "street": "Zaahu Park",
    "city": "Taitiro",
    "state": "HI",
    "zip": "90754"
  },
  "contact": {
    "phone": "(631) 282-6894",
    "servicePhone": "800956421"
  },
  "birthday": "1982-09-16T00:05:58.605Z",
  "ip": "68.73.134.111",
  "foo": "bar",
  "profile": {
    "about": "Viteh ofi ecbeur con fafeb muffap hol baazfi boliwnoz piz wuswekdi hawcukiz. Bi ibugoiso gegek coh tuktince galdijmaz zocce se ve ihwa edebsi hosvih mu. Vu tadev acorekum laf tackijkef vi vaskawjo kah jasup voligda ridhoven pihpoz zit icefof vemvam bic. Huczu ebjoz gouta tehe pe zaziz hiwnan raz ve sovawih kulce obopinke joz had ha hosupeud cipupab konmufwo. Zov nap ece zer ihukorzo gip du wo te mecpo bati gozucu uj. In koge winozi uhiozu cuc zuhvuvse hav hicakjo vujmu feremkoj upivuf enowe poajenem uz wo jokvoojo menoeg seod. Piful efumunma owi un ravake fopheg todfir ila kib po giojije los iz ne dinon po.",
    "bio": "Curkuk docas nasnecbiv re kebdisfaf us meabumog ka kelwehu fuhef berad ahiocze bo. To puv nij abowo tok suhu wa ediwor isubaege duhbiwcu co iceuzu obos. Setivi copu tu ma fazlif jipivu hehsunbih dedcikute om ke pohabraj jirno zaneg. Lojiba hempa zu ecucip tagawupu beke ekziwdi him kew zuspawve kel dacesipem vug vo. Vopooz waog mefah negkofec izaguk sakduwot iwude tidreb nisbo juz lopwero ce onize mo uva ven."
  },
  "apiKey": "6bd980530fd643cefeb641de42448a4ecf81731a842ff44ff3397cfa6a014cbe",
  "currency": {
    "code": "ALL",
    "name": "Albania Lek"
  }
}