{
  "name": "Jeremy Burgess",
  "age": 43,
  "address": {
    "street": "Loduz Street",
    "city": "Focvemca",
    "state": "VA",
    "zip": "02991"
  },
  "contact": {
    "phone": "(688) 737-2525",
    "servicePhone": "800876454"
  },
  "birthday": "1983-09-07T21:20:01.306Z",
  "ip": "191.118.150.64",
  "foo": "bar",
  "profile": {
    "about": "Alofikzoz uhofu huggubvez dokoviwob galawjec ke ug niobime sinjirifo uh hu uceic unejoj vofdul gug vaahije sumzonvu. Ron esowu hir fannolu leul emem rok ziikmo tigubhih vugogoh jomzi lap bocappe itne reujme viwgabi safempuk. Faterdaj izrag vas ihahe fesganu koud lapgu usuahi meuzobet bu wej hunu mil. Tah etuw du bemlosaf buubijaf tip tifwu bebo rak cullewe ho wibfig. Cehvi ishaku donono ammuh zumume gak negurinas nujliaw mij sabofke moz rodtemhut uh ku duvlav lo.",
    "bio": "Furitoja um vosiru tilu ted ruzoldo lehtaoce iceusuw filouk rigtu rem takojuco wiwu mo vegpe mi. Igo fuv kuen ud atiri wevdire mug beruna woserwov ga pimmi zot. Fur ikebij pizbi wogvi kiwcajbo ere zelbamef to su duri ibezot hahle ap borsake tudaah mim puovpit."
  },
  "apiKey": "1819b73350fe70a3190d7eb30824d149fd3c16115a9f712885d6aaffe14db9e1",
  "currency": {
    "code": "HTG",
    "name": "Haiti Gourde"
  }
}